.gitignore
LICENSE
MANIFEST.in
Makefile
README.rst
requirements.txt
setup.py
docs/Makefile
docs/conf.py
docs/index.rst
docs/make.bat
smartsvm/__init__.py
smartsvm/base.py
smartsvm/cross_connections.py
smartsvm/cut.py
smartsvm/divergence.py
smartsvm/error_estimate.py
smartsvm/smartsvm.py
smartsvm/utils.py
smartsvm.egg-info/PKG-INFO
smartsvm.egg-info/SOURCES.txt
smartsvm.egg-info/dependency_links.txt
smartsvm.egg-info/not-zip-safe
smartsvm.egg-info/requires.txt
smartsvm.egg-info/top_level.txt
src/c_multiclass_mst_count.c
src/c_ortho_mst.c
src/multiclass_mst_count.c
src/multiclass_mst_count.pyx
src/ortho_mst.c
src/ortho_mst.pyx
tests/test_base.py
tests/test_cross_connections.py
tests/test_cut.py
tests/test_divergence.py
tests/test_error_estimate.py
tests/test_ortho_mst.py
tests/test_smartsvm.py
tests/test_utils.py