Metadata-Version: 1.1
Name: smartsvm
Version: 1.1.0
Summary: Python package for Meta-Learning and Adaptive Hierarchical Classifier Design
Home-page: https://github.com/HeroResearchGroup/SmartSVM
Author: G.J.J. van den Burg
Author-email: gertjanvandenburg@gmail.com
License: GPL v2
Platform: UNKNOWN
Classifier: Programming Language :: Python :: 2.7
Classifier: Programming Language :: Python :: 3
